bthomehub/__init__.py
bthomehub/client.py
bthomehub/exception.py
bthomehub-2.0.1.dist-info/METADATA
bthomehub-2.0.1.dist-info/RECORD
bthomehub-2.0.1.dist-info/WHEEL
bthomehub-2.0.1.dist-info/top_level.txt
