Metadata-Version: 2.1
Name: bthomehub
Version: 2.0.1
Summary: A Python client that can interact with BT Home Hub routers.
Home-page: https://github.com/onegambler/bthomehub_client
Author: oneGambler
Author-email: UNKNOWN
License: UNLICENSE
Download-URL: https://github.com/onegambler/bthomehub_client/archive/1.0.tar.gz
Keywords: bt home hub,devices list
Platform: UNKNOWN
Requires-Dist: requests (==2.18.3)
